.travis.yml
README.rst
bootstrap.py
buildout.cfg
pre-commit-check.sh
setup.cfg
setup.py
validation-files.yaml
validation-options.yaml
docs/HISTORY.rst
docs/LICENSE.rst
docs/api.rst
docs/conf.py
docs/conventions.rst
docs/env.rst
docs/index.rst
docs/release.rst
src/spinrewriter/__init__.py
src/spinrewriter/exceptions.py
src/spinrewriter/version.txt
src/spinrewriter.egg-info/PKG-INFO
src/spinrewriter.egg-info/SOURCES.txt
src/spinrewriter.egg-info/dependency_links.txt
src/spinrewriter.egg-info/not-zip-safe
src/spinrewriter.egg-info/requires.txt
src/spinrewriter.egg-info/top_level.txt
src/spinrewriter/tests/__init__.py
src/spinrewriter/tests/test_api.py
src/spinrewriter/tests/test_spinrewriter.py