Metadata-Version: 1.0
Name: spinrewriter
Version: 0.1.4
Summary: Python bindings for SpinRewriter API
Home-page: http://www.niteoweb.com
Author: NiteoWeb Ltd.
Author-email: info@niteoweb.com
License: BSD
Keywords: API spinner SpinRewriter
Platform: UNKNOWN
Classifier: Programming Language :: Python
Classifier: Topic :: Internet :: WWW/HTTP
